odoo/addons/l10n_ro_address_extended/README.rst
odoo/addons/l10n_ro_address_extended/__init__.py
odoo/addons/l10n_ro_address_extended/__manifest__.py
odoo/addons/l10n_ro_address_extended/init_hook.py
odoo/addons/l10n_ro_address_extended/i18n/l10n_ro_address_extended.pot
odoo/addons/l10n_ro_address_extended/migrations/14.0.1.1.1/pre-migration.py
odoo/addons/l10n_ro_address_extended/models/__init__.py
odoo/addons/l10n_ro_address_extended/models/res_company.py
odoo/addons/l10n_ro_address_extended/models/res_partner.py
odoo/addons/l10n_ro_address_extended/readme/CONTRIBUTORS.rst
odoo/addons/l10n_ro_address_extended/readme/DESCRIPTION.rst
odoo/addons/l10n_ro_address_extended/readme/INSTALL.rst
odoo/addons/l10n_ro_address_extended/static/description/icon.png
odoo/addons/l10n_ro_address_extended/static/description/index.html
odoo/addons/l10n_ro_address_extended/tests/__init__.py
odoo/addons/l10n_ro_address_extended/tests/test_street_fields.py
odoo/addons/l10n_ro_address_extended/views/res_company_view.xml
odoo/addons/l10n_ro_address_extended/views/res_partner_view.xml
odoo14_addon_l10n_ro_address_extended-14.0.2.3.0.dist-info/METADATA
odoo14_addon_l10n_ro_address_extended-14.0.2.3.0.dist-info/WHEEL
odoo14_addon_l10n_ro_address_extended-14.0.2.3.0.dist-info/top_level.txt
odoo14_addon_l10n_ro_address_extended-14.0.2.3.0.dist-info/RECORD
